mufs/Metrics.py
mufs/Selection.py
mufs/__init__.py
mufs/_version.py
mufs/tests/MUFS_test.py
mufs/tests/Metrics_test.py
mufs/tests/__init__.py
MUFS-0.1.3.dist-info/LICENSE
MUFS-0.1.3.dist-info/METADATA
MUFS-0.1.3.dist-info/WHEEL
MUFS-0.1.3.dist-info/top_level.txt
MUFS-0.1.3.dist-info/RECORD
