Metadata-Version: 2.1
Name: MUFS
Version: 0.1.3
Summary: Multi Feature Selection
Home-page: https://github.com/Doctorado-ML/mufs#mufs
Author: Ricardo Montañana Gómez
Author-email: Ricardo.Montanana@alu.uclm.es
License: MIT License
Project-URL: Code, https://github.com/Doctorado-ML/mufs
Keywords: feature-selection
Platform: UNKNOWN
Classifier: Development Status :: 4 - Beta
Classifier: License :: OSI Approved :: MIT License
Classifier: Programming Language :: Python :: 3.8
Classifier: Programming Language :: Python :: 3.9
Classifier: Programming Language :: Python :: 3.10
Classifier: Natural Language :: English
Classifier: Topic :: Scientific/Engineering :: Artificial Intelligence
Classifier: Intended Audience :: Science/Research
License-File: LICENSE
Requires-Dist: scikit-learn (>0.24)
